README.txt
setup.py
SatchmoBeanstream.egg-info/PKG-INFO
SatchmoBeanstream.egg-info/SOURCES.txt
SatchmoBeanstream.egg-info/dependency_links.txt
SatchmoBeanstream.egg-info/namespace_packages.txt
SatchmoBeanstream.egg-info/requires.txt
SatchmoBeanstream.egg-info/top_level.txt
SatchmoBeanstream.egg-info/zip-safe
satchmobeanstream/__init__.py
satchmobeanstream/beanstream/__init__.py
satchmobeanstream/beanstream/config.py
satchmobeanstream/beanstream/forms.py
satchmobeanstream/beanstream/models.py
satchmobeanstream/beanstream/processor.py
satchmobeanstream/beanstream/tests.py
satchmobeanstream/beanstream/urls.py
satchmobeanstream/beanstream/views.py