Metadata-Version: 1.0
Name: SatchmoBeanstream
Version: 0.2
Summary: Satchmo Beanstream Payment Plugin
Home-page: http://bitbucket.org/benoitcsirois/satchmobeanstream
Author: Benoit Clennett-Sirois
Author-email: benoit@clennett.com
License: LGPL
Platform: UNKNOWN
Classifier: Development Status :: 4 - Beta
Classifier: Environment :: Console
Classifier: Intended Audience :: Developers
Classifier: License :: OSI Approved :: GNU Library or Lesser General Public License (LGPL)
Classifier: Operating System :: OS Independent
Classifier: Programming Language :: Python
Classifier: Programming Language :: Python :: 2.6
Classifier: Programming Language :: Python :: 2.7
Classifier: Topic :: Software Development :: Libraries :: Python Modules
